README.rst
setup.py
wishbone_output_zmqtopic/__init__.py
wishbone_output_zmqtopic/zmqtopicout.py
wishbone_output_zmqtopic.egg-info/PKG-INFO
wishbone_output_zmqtopic.egg-info/SOURCES.txt
wishbone_output_zmqtopic.egg-info/dependency_links.txt
wishbone_output_zmqtopic.egg-info/entry_points.txt
wishbone_output_zmqtopic.egg-info/namespace_packages.txt
wishbone_output_zmqtopic.egg-info/not-zip-safe
wishbone_output_zmqtopic.egg-info/requires.txt
wishbone_output_zmqtopic.egg-info/top_level.txt