Metadata-Version: 1.1
Name: wishbone-output-zmqtopic
Version: 1.0.0
Summary: A Wishbone output module to push events to one or more ZeroMQ topic subscriber sockets
Home-page: https://github.com/smetj/wishbone-output-zmqtopic
Author: Jelle Smet
Author-email: development@smetj.net
License: UNKNOWN
Download-URL: https://github.com/smetj/wishbone-output-zmqtopic/tarball/master
Platform: Linux
Classifier: Development Status :: 5 - Production/Stable
Classifier: License :: OSI Approved :: GNU General Public License v3 or later (GPLv3+)
Classifier: Programming Language :: Python
Classifier: Programming Language :: Python :: 2.7
Classifier: Programming Language :: Python :: Implementation :: PyPy
Classifier: Intended Audience :: Developers
Classifier: Intended Audience :: System Administrators
